NOTICE.txt
flatgeobuf/FlatGeobuf/Column.py
flatgeobuf/FlatGeobuf/ColumnType.py
flatgeobuf/FlatGeobuf/Crs.py
flatgeobuf/FlatGeobuf/Feature.py
flatgeobuf/FlatGeobuf/Geometry.py
flatgeobuf/FlatGeobuf/GeometryType.py
flatgeobuf/FlatGeobuf/Header.py
flatgeobuf/FlatGeobuf/__init__.py
flatgeobuf/__init__.py
flatgeobuf/async_http_reader.py
flatgeobuf/bbox_filter.py
flatgeobuf/column_meta.py
flatgeobuf/config.py
flatgeobuf/constants.py
flatgeobuf/crs_meta.py
flatgeobuf/file_range_client.py
flatgeobuf/file_reader.py
flatgeobuf/generic/__init__.py
flatgeobuf/generic/feature.py
flatgeobuf/generic/featurecollection.py
flatgeobuf/generic/geometry.py
flatgeobuf/geojson/__init__.py
flatgeobuf/geojson/feature.py
flatgeobuf/geojson/featurecollection.py
flatgeobuf/geojson/geometry.py
flatgeobuf/geojson/reader.py
flatgeobuf/header_meta.py
flatgeobuf/http_range_client.py
flatgeobuf/http_reader.py
flatgeobuf/packedrtree.py
flatgeobuf-0.3.1.dist-info/LICENSE.txt
flatgeobuf-0.3.1.dist-info/METADATA
flatgeobuf-0.3.1.dist-info/NOTICE.txt
flatgeobuf-0.3.1.dist-info/WHEEL
flatgeobuf-0.3.1.dist-info/RECORD
