Metadata-Version: 2.1
Name: flatgeobuf
Version: 0.3.1
Summary: Python library for FlatGeobuf
Home-page: https://github.com/ozekik/python-flatgeobuf
License: MIT
Author: Kentaro Ozeki
Author-email: kentaro.ozeki+dev@gmail.com
Requires-Python: >=3.9,<4.0
Classifier: License :: OSI Approved :: MIT License
Classifier: Programming Language :: Python :: 3
Classifier: Programming Language :: Python :: 3.9
Classifier: Programming Language :: Python :: 3.10
Classifier: Programming Language :: Python :: 3.11
Classifier: Programming Language :: Python :: 3.12
Requires-Dist: flatbuffers (>=24.3.7,<25.0.0)
Requires-Dist: geojson (>=3.1.0,<4.0.0)
Requires-Dist: numpy (>=1.26.1,<3.0.0)
Requires-Dist: shapely (>=1.8.2)
Project-URL: Repository, https://github.com/ozekik/python-flatgeobuf
